{
    "title": "El Gobierno apunta que el confinamiento para los asintomáticos sería voluntario",
    "subtitle": "El Ejecutivo busca fórmulas legales para ver cómo actuar con aquellas personas que no quieran aislarse",
    "author": "Carlos E. Cué",
    "date": "2020-04-07",
    "time": "08:00 UTC",
    "content": "- Pinche aquí para suscribirse a la newsletter diaria sobre la pandemia",
    "processed": [
        "pinch",
        "suscrib",
        "newslett",
        "diari",
        "pandemi"
    ]
}